geochemseek/TTG_Ternary_Plot.py
geochemseek/__init__.py
geochemseek/calculate_closure_T.py
geochemseek/classification/__init__.py
geochemseek/classification/jensen_plot.py
geochemseek/classification/ttg_ternary_plot.py
geochemseek/config/__init__.py
geochemseek/config/config.py
geochemseek/geothermobarometry/__init__.py
geochemseek/geothermobarometry/rutile.py
geochemseek/isotoe/__init__.py
geochemseek/isotoe/hf_w.py
geochemseek/major_element/__init__.py
geochemseek/major_element/cia_plot.py
geochemseek/major_element/k_si_plot.py
geochemseek/major_element/tas_plot.py
geochemseek/trace_element/__init__.py
geochemseek/trace_element/ree.py
geochemseek/trace_element/spider.py
geochemseek/utils/__init__.py
geochemseek/utils/add_subplot_labels.py
geochemseek/utils/annotate.py
geochemseek/utils/error_ellipse.py
geochemseek/utils/ternary_plot.py
geochemseek-0.0.3.dist-info/LICENSE
geochemseek-0.0.3.dist-info/METADATA
geochemseek-0.0.3.dist-info/WHEEL
geochemseek-0.0.3.dist-info/top_level.txt
geochemseek-0.0.3.dist-info/RECORD
