Metadata-Version: 2.1
Name: geochemseek
Version: 0.0.3
Summary: A python package for geochemical toolkit
Home-page: https://github.com/QingFengMei/geochemseek
Author: QingFengMei
Author-email: qingfengmei@foxmail.com
License: MIT
Classifier: Programming Language :: Python :: 3
Classifier: License :: OSI Approved :: MIT License
Classifier: Operating System :: OS Independent
Requires-Python: >=3.12
License-File: LICENSE
Requires-Dist: pandas
Requires-Dist: matplotlib
Requires-Dist: numpy
